{
  "project_info": {
    "project_number": "700380707815",
    "project_id": "upmhrth-e3ddd",
    "storage_bucket": "upmhrth-e3ddd.appspot.com"
  },
  "client": [
    {
      "client_info": {
        "mobilesdk_app_id": "1:700380707815:android:64b2a7cc8fd6de40731b42",
        "android_client_info": {
          "package_name": "com.example.upmhrth"
        }
      },
      "oauth_client": [
        {
          "client_id": "700380707815-to6egf4r8gar5p3c47c7nq6v7bragb46.apps.googleusercontent.com",
          "client_type": 3
        }
      ],
      "api_key": [
        {
          "current_key": "AIzaSyAANexdVyqndCLBhLnb9Dths5DMVjrZ7KI"
        }
      ],
      "services": {
        "appinvite_service": {
          "other_platform_oauth_client": [
            {
              "client_id": "700380707815-to6egf4r8gar5p3c47c7nq6v7bragb46.apps.googleusercontent.com",
              "client_type": 3
            }
          ]
        }
      }
    }
  ],
  "configuration_version": "1"
}